<?xml version="1.0" encoding="utf-8"?>
<translations>
   <translation id="sso_modal_title" qtlid="315956">OVH - Autentifikavimas</translation>
   <translation id="sso_modal_loading" qtlid="8410">Įkraunama...</translation>
   <translation id="sso_modal_user_title" qtlid="315969">Jūs buvote prisijungęs kaip:</translation>
   <translation id="sso_modal_currentuser_title" qtlid="315982">Šiuo metu esate prisijungęs kaip:</translation>
   <translation id="sso_modal_disconnected" qtlid="315995">Šiuo metu esate atsijungęs.</translation>
   <translation id="sso_modal_what" qtlid="62558">Ką norite atlikti?</translation>
   <translation id="sso_modal_action_reload" qtlid="344084">Tęsti kaip <strong>{{name}}</strong></translation>
   <translation id="sso_modal_action_logout" qtlid="316021">Eiti į autentifikavimo puslapį</translation>
</translations>
