<?xml version="1.0" encoding="utf-8"?>
<translations>
   <translation id="ua_unit_size_B" qtlid="121975">b</translation>
   <translation id="ua_unit_size_KB" qtlid="121987">kb</translation>
   <translation id="ua_unit_size_MB" qtlid="48878">MB</translation>
   <translation id="ua_unit_size_GB" qtlid="48890">GB</translation>
   <translation id="ua_unit_size_TB" qtlid="70121">TB</translation>
   <translation id="ua_unit_size_PB" qtlid="121999">PB</translation>
   <translation id="ua_unit_size_EB" qtlid="122011">EB</translation>
   <translation id="ua_unit_size_ZB" qtlid="122023">ZB</translation>
   <translation id="ua_unit_size_YB" qtlid="122035">YB</translation>
</translations>
