<?xml version="1.0" encoding="utf-8"?>
<translations>
   <translation id="sidebar_menu" qtlid="304576">Meniu</translation>
   <translation id="sidebar_menu_order_actions" qtlid="43558">Užsakyti</translation>
   <translation id="sidebar_menu_search" qtlid="37659">Ieškoti</translation>
   <translation id="sidebar_menu_search_no_results" qtlid="345481">Nerasta jokių rezultatų.</translation>
   <translation id="sidebar_menu_search_loading" qtlid="345494">Ieškoma...</translation>
   <translation id="sidebar_menu_error_retry" qtlid="238193">Bandyti dar kartą</translation>
</translations>
